staphscope/__init__.py
staphscope/cli.py
staphscope/core.py
staphscope-0.2.1.dist-info/licenses/LICENSE
tests/__init__.py
tests/test_staphscope.py
staphscope-0.2.1.dist-info/METADATA
staphscope-0.2.1.dist-info/WHEEL
staphscope-0.2.1.dist-info/entry_points.txt
staphscope-0.2.1.dist-info/top_level.txt
staphscope-0.2.1.dist-info/RECORD
