Metadata-Version: 2.4
Name: staphscope
Version: 0.2.1
Summary: Unified MLST + spa + SCCmec typing tool for Staphylococcus aureus
Home-page: https://github.com/bbeckley-hub/staphscope-typing-tool
Author: Brown Beckley
Author-email: brownbeckley94@gmail.com
Project-URL: Source, https://github.com/bbeckley-hub/staphscope-typing-tool
Project-URL: Bug Reports, https://github.com/bbeckley-hub/staphscope-typing-tool/issues
Keywords: staphylococcus aureus typing mlst spa sccmec bioinformatics
Classifier: Programming Language :: Python :: 3
Classifier: License :: OSI Approved :: MIT License
Classifier: Operating System :: OS Independent
Classifier: Topic :: Scientific/Engineering :: Bio-Informatics
Requires-Python: >=3.7
License-File: LICENSE
Requires-Dist: biopython>=1.79
Requires-Dist: pandas>=1.3.0
Requires-Dist: click>=8.0.0
Dynamic: author
Dynamic: author-email
Dynamic: classifier
Dynamic: description
Dynamic: description-content-type
Dynamic: home-page
Dynamic: keywords
Dynamic: license-file
Dynamic: project-url
Dynamic: requires-dist
Dynamic: requires-python
Dynamic: summary
